{
  "posts": [
    {
      "id": 1,
      "title": "Ejercicio Json-Server",
      "author": "typicode"
    },
    {
      "id": 2,
      "title": "Ejercicios varios",
      "author": "javiererce"
    },
    {
      "id": 3,
      "title": "Ejercicios simples",
      "author": "alejandra bessi"
    },
    {
      "id": 5,
      "title": "0.23675761428707265",
      "author": "Author: 0.23675761428707265"
    },
    {
      "id": 4,
      "title": "0.35357928245769554",
      "author": "Author: 0.35357928245769554"
    },
    {
      "id": 27,
      "title": "Ejercicios varios",
      "author": "javiererce"
    },
    {
      "id": 23,
      "title": "Ejercicios varios",
      "author": "javiererce"
    },
    {
      "id": 29,
      "title": "Ejercicios varios",
      "author": "javiererce"
    },
    {
      "id": 28,
      "title": "Ejercicios varios",
      "author": "javiererce"
    },
    {
      "id": 30,
      "title": "Ejercicios varios",
      "author": "javiererce"
    },
    {
      "id": 31,
      "title": "Ejercicios varios",
      "author": "javiererce"
    },
    {
      "id": 32,
      "title": "Ejercicios varios",
      "author": "javiererce"
    },
    {
      "id": 34,
      "title": "Ejercicios varios",
      "author": "javiererce"
    },
    {
      "id": 37,
      "title": "Ejercicios varios",
      "author": "javiererce"
    },
    {
      "id": 39,
      "title": "Ejercicios varios",
      "author": "javiererce"
    },
    {
      "id": 40,
      "title": "Ejercicios varios",
      "author": "javiererce"
    },
    {
      "id": 41,
      "title": "Ejercicios varios",
      "author": "javiererce"
    },
    {
      "id": 45,
      "title": "Ejercicios varios",
      "author": "javiererce"
    },
    {
      "id": 47,
      "title": "Ejercicios varios",
      "author": "javiererce"
    },
    {
      "id": 48,
      "title": "Ejercicios varios",
      "author": "javiererce"
    },
    {
      "id": 49,
      "title": "Ejercicios varios",
      "author": "javiererce"
    },
    {
      "id": 50,
      "title": "Ejercicios varios",
      "author": "javiererce"
    },
    {
      "id": 51,
      "title": "Ejercicios varios",
      "author": "javiererce"
    },
    {
      "id": 55,
      "title": "Ejercicios varios",
      "author": "javiererce"
    },
    {
      "id": 57,
      "title": "Ejercicios varios",
      "author": "javiererce"
    },
    {
      "id": 59,
      "title": "Ejercicios varios",
      "author": "javiererce"
    },
    {
      "id": 60,
      "title": "Ejercicios varios",
      "author": "javiererce"
    },
    {
      "id": 80,
      "title": "Ejercicios varios",
      "author": "javiererce"
    }
  ],
  "comments": [
    {
      "id": 1,
      "body": "Cypress",
      "postId": 1
    }
  ],
  "profile": {
    "name": "Maximiliano"
  }
}